financial_agent/__init__.py
financial_agent/agent.py
financial_agent/chunk_utils.py
financial_agent/vector_db.py
financial_agent-0.1.0.dist-info/licenses/LICENSE
financial_agent-0.1.0.dist-info/METADATA
financial_agent-0.1.0.dist-info/WHEEL
financial_agent-0.1.0.dist-info/top_level.txt
financial_agent-0.1.0.dist-info/RECORD
