Metadata-Version: 2.4
Name: financial-agent
Version: 0.1.0
Summary: RAG-powered agent for SEC financial filings
License: MIT
Requires-Python: >=3.9
License-File: LICENSE
Requires-Dist: numpy
Requires-Dist: faiss-cpu
Requires-Dist: google-genai
Requires-Dist: pyyaml
Requires-Dist: python-dotenv
Provides-Extra: dev
Requires-Dist: pytest; extra == "dev"
Provides-Extra: pipeline
Requires-Dist: sec-api; extra == "pipeline"
Requires-Dist: beautifulsoup4; extra == "pipeline"
Requires-Dist: spacy; extra == "pipeline"
Requires-Dist: tiktoken; extra == "pipeline"
Requires-Dist: yfinance; extra == "pipeline"
Requires-Dist: pandas; extra == "pipeline"
Requires-Dist: google-cloud-aiplatform; extra == "pipeline"
Dynamic: license-file
